{
    "1": "Anti-Mage",
    "2": "Axe",
    "3": "Bane",
    "4": "Bloodseeker",
    "5": "Crystal Maiden",
    "6": "Drow Ranger",
    "7": "Earthshaker",
    "8": "Juggernaut",
    "9": "Mirana",
    "10": "Morphling",
    "11": "Naga Siren",
    "12": "Nature's Prophet",
    "13": "Necrophos",
    "14": "Pudge",
    "15": "Riki",
    "16": "Shadow Fiend",
    "17": "Slardar",
    "18": "Snapfire",
    "19": "Spectre",
    "20": "Spirit Breaker",
    "21": "Storm Spirit",
    "22": "Sven",
    "23": "Tidehunter",
    "24": "Timbersaw",
    "25": "Tinker",
    "26": "Tiny",
    "27": "Treant Protector",
    "28": "Troll Warlord",
    "29": "Ursa",
    "30": "Venomancer",
    "31": "Viper",
    "32": "Warlock",
    "33": "Weaver",
    "34": "Kunkka",
    "35": "Pugna",
    "36": "Queen of Pain",
    "37": "Death Prophet",
    "38": "Disruptor",
    "39": "Nyx Assassin",
    "40": "Ogre Magi",
    "41": "Oracle",
    "42": "Silencer",
    "43": "Tusk",
    "44": "Void Spirit",
    "45": "Witch Doctor",
    "46": "Wraith King",
    "47": "Abaddon",
    "48": "Alchemist",
    "49": "Bristleback",
    "50": "Centaur Warrunner",
    "51": "Chaos Knight",
    "52": "Dark Seer",
    "53": "Disraptor",
    "54": "Doom",
    "55": "Dragon Knight",
    "56": "Earth Spirit",
    "57": "Ember Spirit",
    "58": "Enchantress",
    "59": "Enigma",
    "60": "Faceless Void",
    "61": "Gyrocopter",
    "62": "Huskar",
    "63": "Invoker",
    "64": "Io",
    "65": "Kunkka",
    "66": "Legion Commander",
    "67": "Lich",
    "68": "Lifestealer",
    "69": "Lina",
    "70": "Lion",
    "71": "Meepo",
    "72": "Monkey King",
    "73": "Naga Siren",
    "74": "Necrophos",
    "75": "Ogre Magi",
    "76": "Phantom Assassin",
    "77": "Phantom Lancer",
    "78": "Pugna",
    "79": "Pudge",
    "80": "Riki",
    "81": "Rubick",
    "82": "Sand King",
    "83": "Shadow Demon",
    "84": "Shadow Fiend",
    "85": "Silencer",
    "86": "Slardar",
    "87": "Sniper",
    "88": "Spirit Breaker",
    "89": "Terrorblade",
    "90": "Tidehunter",
    "91": "Timbersaw",
    "92": "Tinker",
    "93": "Treant Protector",
    "94": "Troll Warlord",
    "95": "Ursa",
    "96": "Venomancer",
    "97": "Viper",
    "98": "Warlock",
    "99": "Weaver"
}
